{
    "modules": [
        {
            "config": {
                "position": [
                    35,
                    65
                ]
            },
            "name": "New Model Object",
            "value": {
                "actionGroup": {
                    "_default0_list": true,
                    "_default1_show": true,
                    "_default2_new_create": false,
                    "_default3_edit_update": false,
                    "_default4_delete": false,
                    "customActions": []
                },
                "name": "Arrangement",
                "objectsettings": {
                    "addDeletedField": true,
                    "addHiddenField": true,
                    "addStarttimeEndtimeFields": true,
                    "aggregateRoot": true,
                    "categorizable": true,
                    "description": "",
                    "mapToTable": "",
                    "parentClass": "",
                    "sorting": true,
                    "type": "Entity",
                    "uid": "1410362557876"
                },
                "propertyGroup": {
                    "properties": [
                        {
                            "allowedFileTypes": "",
                            "maxItems": "1",
                            "propertyDescription": "",
                            "propertyIsExcludeField": false,
                            "propertyIsRequired": true,
                            "propertyName": "titel",
                            "propertyType": "String",
                            "uid": "679384637432"
                        },
                        {
                            "allowedFileTypes": "",
                            "maxItems": "1",
                            "propertyDescription": "",
                            "propertyIsExcludeField": false,
                            "propertyIsRequired": false,
                            "propertyName": "beskrivelse",
                            "propertyType": "RichText",
                            "uid": "1372983523366"
                        },
                        {
                            "allowedFileTypes": "",
                            "maxItems": "1",
                            "propertyDescription": "Start dato",
                            "propertyIsExcludeField": false,
                            "propertyIsRequired": false,
                            "propertyName": "startDato",
                            "propertyType": "NativeDate",
                            "uid": "663467242050"
                        },
                        {
                            "allowedFileTypes": "",
                            "maxItems": "1",
                            "propertyDescription": "Slut dato",
                            "propertyIsExcludeField": false,
                            "propertyIsRequired": false,
                            "propertyName": "slutDato",
                            "propertyType": "NativeDate",
                            "uid": "715165333304"
                        },
                        {
                            "allowedFileTypes": "",
                            "maxItems": "1",
                            "propertyDescription": "",
                            "propertyIsExcludeField": false,
                            "propertyIsRequired": false,
                            "propertyName": "pris",
                            "propertyType": "String",
                            "uid": "1055031545246"
                        },
                        {
                            "allowedFileTypes": "",
                            "maxItems": "1",
                            "propertyDescription": "\u00c5ben for tilmelding",
                            "propertyIsExcludeField": false,
                            "propertyIsRequired": false,
                            "propertyName": "openForParticipants",
                            "propertyType": "Boolean",
                            "uid": "1373358391619"
                        },
                        {
                            "allowedFileTypes": "",
                            "maxItems": "1",
                            "propertyDescription": "",
                            "propertyIsExcludeField": false,
                            "propertyIsRequired": false,
                            "propertyName": "tilmeldingstekst",
                            "propertyType": "String",
                            "uid": "695429266983"
                        },
                        {
                            "allowedFileTypes": "",
                            "maxItems": "1",
                            "propertyDescription": "M\u00e5lgruppe",
                            "propertyIsExcludeField": false,
                            "propertyIsRequired": false,
                            "propertyName": "maalgruppe",
                            "propertyType": "String",
                            "uid": "1363490015593"
                        },
                        {
                            "allowedFileTypes": "",
                            "maxItems": "1",
                            "propertyDescription": "Registrerings dato",
                            "propertyIsExcludeField": false,
                            "propertyIsRequired": false,
                            "propertyName": "registreringsDato",
                            "propertyType": "NativeDate",
                            "uid": "485715133410"
                        }
                    ]
                },
                "relationGroup": {
                    "relations": [
                        {
                            "foreignRelationClass": "",
                            "lazyLoading": false,
                            "propertyIsExcludeField": false,
                            "relationDescription": "",
                            "relationName": "sted",
                            "relationType": "zeroToOne",
                            "relationWire": "[wired]",
                            "uid": "189389805341"
                        }
                    ]
                }
            }
        },
        {
            "config": {
                "position": [
                    535,
                    66
                ]
            },
            "name": "New Model Object",
            "value": {
                "actionGroup": {
                    "_default0_list": true,
                    "_default1_show": true,
                    "_default2_new_create": false,
                    "_default3_edit_update": false,
                    "_default4_delete": false,
                    "customActions": []
                },
                "name": "Sted",
                "objectsettings": {
                    "addDeletedField": true,
                    "addHiddenField": true,
                    "addStarttimeEndtimeFields": true,
                    "aggregateRoot": false,
                    "categorizable": false,
                    "description": "",
                    "mapToTable": "",
                    "parentClass": "",
                    "sorting": false,
                    "type": "Entity",
                    "uid": "1306055127117"
                },
                "propertyGroup": {
                    "properties": [
                        {
                            "allowedFileTypes": "",
                            "maxItems": "1",
                            "propertyDescription": "",
                            "propertyIsExcludeField": false,
                            "propertyIsRequired": true,
                            "propertyName": "navn",
                            "propertyType": "String",
                            "uid": "783828694687"
                        },
                        {
                            "allowedFileTypes": "",
                            "maxItems": "1",
                            "propertyDescription": "",
                            "propertyIsExcludeField": false,
                            "propertyIsRequired": false,
                            "propertyName": "gadenavnOgNummer",
                            "propertyType": "String",
                            "uid": "1275056483861"
                        },
                        {
                            "allowedFileTypes": "",
                            "maxItems": "1",
                            "propertyDescription": "",
                            "propertyIsExcludeField": false,
                            "propertyIsRequired": false,
                            "propertyName": "postNummer",
                            "propertyType": "String",
                            "uid": "1127782135108"
                        },
                        {
                            "allowedFileTypes": "",
                            "maxItems": "1",
                            "propertyDescription": "By",
                            "propertyIsExcludeField": false,
                            "propertyIsRequired": false,
                            "propertyName": "bynavn",
                            "propertyType": "String",
                            "uid": "1397595176939"
                        },
                        {
                            "allowedFileTypes": "",
                            "maxItems": "1",
                            "propertyDescription": "",
                            "propertyIsExcludeField": false,
                            "propertyIsRequired": false,
                            "propertyName": "url",
                            "propertyType": "String",
                            "uid": "469632830574"
                        }
                    ]
                },
                "relationGroup": {
                    "relations": []
                }
            }
        }
    ],
    "properties": {
        "backendModules": [],
        "description": "Arrangements plugin for DUK",
        "emConf": {
            "category": "plugin",
            "custom_category": "",
            "dependsOn": "typo3 => 6.2\n",
            "disableLocalization": true,
            "disableVersioning": true,
            "sourceLanguage": "da",
            "state": "alpha",
            "targetVersion": "6.2",
            "version": "0.1"
        },
        "extensionKey": "arrangementer",
        "name": "Arrangementer",
        "originalExtensionKey": "arrangementer",
        "persons": [
            {
                "company": "ShuffleBee",
                "email": "stefan@shufflebee.dk",
                "name": "Stefan Kreisberg",
                "role": "Developer"
            },
            {
                "company": "DUK",
                "email": "michael@duk.dk",
                "name": "Michael H\u00f8ier Clausen",
                "role": "Product Manager"
            }
        ],
        "plugins": [
            {
                "actions": {
                    "controllerActionCombinations": "",
                    "noncacheableActions": "",
                    "switchableActions": ""
                },
                "key": "arrangement",
                "name": "Arrangementer"
            }
        ],
        "vendorName": "DUK"
    },
    "wires": [
        {
            "src": {
                "moduleId": 0,
                "terminal": "relationWire_0",
                "uid": "189389805341"
            },
            "tgt": {
                "moduleId": 1,
                "terminal": "SOURCES",
                "uid": "1306055127117"
            }
        }
    ],
    "log": {
        "last_modified": "2015-06-01 08:43",
        "extension_builder_version": "6.2.0",
        "be_user": "Stefan Kreisberg (56)"
    }
}